Workbook
Name FiscalYearEnd: Assumptions!$C$3
Name FiscalYearStart: Assumptions!$C$2
Name InflationRate: Assumptions!$C$9
Name OperatingDays: Assumptions!$C$4
Name PayrollTaxesRate: Assumptions!$C$8
Name ProgramHoursPerWeek: Assumptions!$C$5
Name StaffBenefitsRate: Assumptions!$C$7
Name StartingCash: Assumptions!$C$6
Name UtilitiesInflationRate: Assumptions!$C$10

Sheet Assumptions
A1: Category | B1: Driver | C1: Value | D1: Units | E1: Status | F1: Owner | G1: Notes
A2: Fiscal Settings | B2: FiscalYearStart | C2: 45962 | D2: date | E2: Placeholder | F2: Matthew | G2: Confirm with City
A3: Fiscal Settings | B3: FiscalYearEnd | C3: 46326 | D3: date | E3: Placeholder | F3: Matthew | G3: Confirm with City
A4: Operations | B4: OperatingDays | C4: =NETWORKDAYS(FiscalYearStart,FiscalYearEnd) | D4: days | E4: Placeholder | F4: Matthew | G4: NETWORKDAYS once holiday list ready
A5: Operations | B5: ProgramHoursPerWeek | C5: 35 | D5: hours | E5: Placeholder | F5: Program Lead | G5: Update after schedule planning
A6: Finance | B6: StartingCash | C6: 0 | D6: USD | E6: Placeholder | F6: City | G6: Confirm start-up funding
A7: HR | B7: StaffBenefitsRate | C7: 0.18 | D7: % | E7: Placeholder | F7: HR | G7: Include health & retirement
A8: HR | B8: PayrollTaxesRate | C8: 0.08 | D8: % | E8: Placeholder | F8: Finance | G8: Confirm employer tax load
A9: Finance | B9: InflationRate | C9: 0.03 | D9: % | E9: Placeholder | F9: Finance | G9: General inflation assumption
A10: Facilities | B10: UtilitiesInflationRate | C10: 0.04 | D10: % | E10: Placeholder | F10: Facilities | G10: Energy costs trending

Sheet Enrollment & Staffing
A1: Period | B1: Position | C1: Hours/Week | D1: Weeks | E1: Total Hours | F1: Headcount | G1: FTE per Person | H1: Total FTE | I1: Notes | J1: Notes
A2: Standard School Year
A3: Standard (38 weeks) | B3: Program Director | C3: 40 | D3: 38 | E3: =C3*D3 | F3: 1 | G3: =E3/2080 | H3: =F3*G3 | I3: NECESSITY - Full-time year-round
A4: Standard (38 weeks) | B4: Director of Youth Development | C4: 40 | D4: 38 | E4: =C4*D4 | F4: 1 | G4: =E4/2080 | H4: =F4*G4 | I4: NECESSITY - Full-time year-round
A5: Standard (38 weeks) | B5: Youth Mentors (2 positions) | C5: 20 | D5: 38 | E5: =C5*D5 | F5: 2 | G5: =E5/2080 | H5: =F5*G5 | I5: NECESSITY - 2 part-time mentors
A6: Standard (38 weeks) | B6: Additional Youth Mentors (2) | C6: 20 | D6: 38 | E6: =C6*D6 | F6: 2 | G6: =E6/2080 | H6: =F6*G6 | I6: IDEAL - 2 additional part-time
A7: Standard (38 weeks) | B7: Teen Coordinator | C7: 30 | D7: 38 | E7: =C7*D7 | F7: 1 | G7: =E7/2080 | H7: =F7*G7 | I7: IDEAL - Part-time teen programming
A9: Extended Hours Period (Summer)
A10: Extended (14 weeks) | B10: Program Director | C10: 40 | D10: 14 | E10: =C10*D10 | F10: 1 | G10: =E10/2080 | H10: =F10*G10 | I10: NECESSITY - Full-time year-round
A11: Extended (14 weeks) | B11: Director of Youth Development | C11: 40 | D11: 14 | E11: =C11*D11 | F11: 1 | G11: =E11/2080 | H11: =F11*G11 | I11: NECESSITY - Full-time year-round
A12: Extended (14 weeks) | B12: Youth Mentors (2 positions) | C12: 40 | D12: 14 | E12: =C12*D12 | F12: 2 | G12: =E12/2080 | H12: =F12*G12 | I12: NECESSITY - 2 full-time summer
A13: Extended (14 weeks) | B13: Additional Youth Mentors (2) | C13: 40 | D13: 14 | E13: =C13*D13 | F13: 2 | G13: =E13/2080 | H13: =F13*G13 | I13: IDEAL - 2 additional full-time summer
A14: Extended (14 weeks) | B14: Teen Coordinator | C14: 40 | D14: 14 | E14: =C14*D14 | F14: 1 | G14: =E14/2080 | H14: =F14*G14 | I14: IDEAL - Full-time summer
A16: ANNUAL TOTALS
B17: Program Director | E17: =E3+E10 | H17: =H3+H10 | I17: NECESSITY: 52 weeks @ 1.0 FTE
B18: Director of Youth Development | E18: =E4+E11 | H18: =H4+H11 | I18: NECESSITY: 52 weeks @ 1.0 FTE
B19: Youth Mentors (2 required) | E19: =E5+E12 | H19: =H5+H12 | I19: NECESSITY: 2 positions = 1.269 FTE
B20: Additional Youth Mentors (2) | E20: =E6+E13 | H20: =H6+H13 | I20: IDEAL: 2 positions = 1.269 FTE
B21: Teen Coordinator | E21: =E7+E14 | H21: =H7+H14 | I21: IDEAL: Variable hours = 0.817 FTE

Sheet Staffing Costs
A1: Role | B1: FTE | C1: Hourly Rate | D1: Annual Salary | E1: Benefits % | F1: Total Compensation | G1: Funding Source | H1: Placeholder? | I1: Notes | J1: Budget Scenario
A2: Program Director | B2: 1 | D2: 50000 | E2: 0.25 | F2: =D2*(1+E2) | G2: City Allocation | H2: Necessity | I2: Full-time salaried, 40 hrs/week year-round | J2: Necessity
A3: Director of Youth Development | B3: 1 | D3: 50000 | E3: 0.25 | F3: =D3*(1+E3) | G3: City Allocation | H3: Necessity | I3: Full-time salaried, 40 hrs/week year-round | J3: Necessity
A4: Youth Mentors (2 positions) | B4: 1.269 | C4: 20 | D4: 52800 | E4: 0.18 | F4: =D4*(1+E4+Assumptions!$C$8) | G4: Program Fees | H4: Necessity | I4: 20 hrs/wk (38 wks) + 40 hrs/wk (14 wks) × 2 staff | J4: Necessity
A6: Additional Youth Mentors (2 positions) | B6: 1.269 | C6: 20 | D6: 52800 | E6: 0.18 | F6: =D6*(1+E6+Assumptions!$C$8) | G6: Program Fees | H6: Ideal | I6: Same schedule as first 2 mentors × 2 more staff | J6: Ideal
A7: Teen Coordinator | B7: 0.817 | C7: 22 | D7: 37400 | E7: 0.18 | F7: =D7*(1+E7+Assumptions!$C$8) | G7: Grants | H7: Ideal | I7: 30 hrs/wk (38 wks) + 40 hrs/wk (14 wks) | J7: Ideal
A9: NECESSITY BUDGET TOTAL | F9: =F2+F3+F4 | I9: 2 Directors + 2 Youth Mentors (required staff)
A10: IDEAL BUDGET TOTAL | F10: =F2+F3+F4+F6+F7 | I10: Add 2 more Youth Mentors + Teen Coordinator (full staffing)

Sheet Expense Detail
A1: Category | B1: Line Item | C1: Cost Driver | D1: Nov | E1: Dec | F1: Jan | G1: Feb | H1: Mar | I1: Apr | J1: May | K1: Jun | L1: Jul | M1: Aug | N1: Sep | O1: Oct | P1: Annual Total | Q1: Budget Type | R1: Notes
A2: Personnel
A3: Personnel | B3: Program Director | C3: Salaried | D3: ='Staffing Costs'!F2/12 | E3: ='Staffing Costs'!F2/12 | F3: ='Staffing Costs'!F2/12 | G3: ='Staffing Costs'!F2/12 | H3: ='Staffing Costs'!F2/12 | I3: ='Staffing Costs'!F2/12 | J3: ='Staffing Costs'!F2/12 | K3: ='Staffing Costs'!F2/12 | L3: ='Staffing Costs'!F2/12 | M3: ='Staffing Costs'!F2/12 | N3: ='Staffing Costs'!F2/12 | O3: ='Staffing Costs'!F2/12 | P3: ='Staffing Costs'!F2 | Q3: Necessity | R3: Full-time salaried
A4: Personnel | B4: Director of Youth Development | C4: Salaried | D4: ='Staffing Costs'!F3/12 | E4: ='Staffing Costs'!F3/12 | F4: ='Staffing Costs'!F3/12 | G4: ='Staffing Costs'!F3/12 | H4: ='Staffing Costs'!F3/12 | I4: ='Staffing Costs'!F3/12 | J4: ='Staffing Costs'!F3/12 | K4: ='Staffing Costs'!F3/12 | L4: ='Staffing Costs'!F3/12 | M4: ='Staffing Costs'!F3/12 | N4: ='Staffing Costs'!F3/12 | O4: ='Staffing Costs'!F3/12 | P4: ='Staffing Costs'!F3 | Q4: Necessity | R4: Full-time salaried
A5: Personnel | B5: Youth Mentors (2 positions) | C5: Hourly | D5: ='Staffing Costs'!F4/12 | E5: ='Staffing Costs'!F4/12 | F5: ='Staffing Costs'!F4/12 | G5: ='Staffing Costs'!F4/12 | H5: ='Staffing Costs'!F4/12 | I5: ='Staffing Costs'!F4/12 | J5: ='Staffing Costs'!F4/12 | K5: ='Staffing Costs'!F4/12 | L5: ='Staffing Costs'!F4/12 | M5: ='Staffing Costs'!F4/12 | N5: ='Staffing Costs'!F4/12 | O5: ='Staffing Costs'!F4/12 | P5: ='Staffing Costs'!F4 | Q5: Necessity | R5: Required staffing
A6: Personnel | B6: Additional Youth Mentors (2) | C6: Hourly | D6: ='Staffing Costs'!F6/12 | E6: ='Staffing Costs'!F6/12 | F6: ='Staffing Costs'!F6/12 | G6: ='Staffing Costs'!F6/12 | H6: ='Staffing Costs'!F6/12 | I6: ='Staffing Costs'!F6/12 | J6: ='Staffing Costs'!F6/12 | K6: ='Staffing Costs'!F6/12 | L6: ='Staffing Costs'!F6/12 | M6: ='Staffing Costs'!F6/12 | N6: ='Staffing Costs'!F6/12 | O6: ='Staffing Costs'!F6/12 | P6: ='Staffing Costs'!F6 | Q6: Ideal | R6: For expanded programming
A7: Personnel | B7: Teen Coordinator | C7: Hourly | D7: ='Staffing Costs'!F7/12 | E7: ='Staffing Costs'!F7/12 | F7: ='Staffing Costs'!F7/12 | G7: ='Staffing Costs'!F7/12 | H7: ='Staffing Costs'!F7/12 | I7: ='Staffing Costs'!F7/12 | J7: ='Staffing Costs'!F7/12 | K7: ='Staffing Costs'!F7/12 | L7: ='Staffing Costs'!F7/12 | M7: ='Staffing Costs'!F7/12 | N7: ='Staffing Costs'!F7/12 | O7: ='Staffing Costs'!F7/12 | P7: ='Staffing Costs'!F7 | Q7: Ideal | R7: Teen programming specialist
A9: Program Expenses
A10: Program | B10: Meals/Snacks | C10: Per participant | D10: 0 | E10: 0 | F10: 0 | G10: 0 | H10: 0 | I10: 0 | J10: 0 | K10: 0 | L10: 0 | M10: 0 | N10: 0 | O10: 0 | P10: =SUM(D10:O10) | Q10: Both | R10: Need vendor quote
A11: Program | B11: Program Supplies | C11: Estimated | D11: 400 | E11: 400 | F11: 400 | G11: 400 | H11: 400 | I11: 400 | J11: 400 | K11: 400 | L11: 400 | M11: 400 | N11: 400 | O11: 400 | P11: =SUM(D11:O11) | Q11: Both | R11: Placeholder
A13: Facility Expenses
A14: Facilities | B14: Facility Rent/Lease | C14: Monthly | D14: 1600 | E14: 1600 | F14: 1600 | G14: 1600 | H14: 1600 | I14: 1600 | J14: 1600 | K14: 1600 | L14: 1600 | M14: 1600 | N14: 1600 | O14: 1600 | P14: =SUM(D14:O14) | Q14: Both | R14: Confirm with City
A15: Facilities | B15: Utilities | C15: City in-kind | D15: 0 | E15: 0 | F15: 0 | G15: 0 | H15: 0 | I15: 0 | J15: 0 | K15: 0 | L15: 0 | M15: 0 | N15: 0 | O15: 0 | P15: =SUM(D15:O15) | Q15: Both | R15: Covered by City
A17: Administrative
A18: Administrative | B18: Insurance (Liability & D&O) | C18: Annual premium | D18: 2500 | E18: 2500 | F18: 2500 | G18: 2500 | H18: 2500 | I18: 2500 | J18: 2500 | K18: 2500 | L18: 2500 | M18: 2500 | N18: 2500 | O18: 2500 | P18: =SUM(D18:O18) | Q18: Both | R18: Need broker quote
A21: NECESSITY BUDGET TOTAL | D21: =D3+D4+D5+D10+D11+D14+D15+D18 | E21: =E3+E4+E5+E10+E11+E14+E15+E18 | F21: =F3+F4+F5+F10+F11+F14+F15+F18 | G21: =G3+G4+G5+G10+G11+G14+G15+G18 | H21: =H3+H4+H5+H10+H11+H14+H15+H18 | I21: =I3+I4+I5+I10+I11+I14+I15+I18 | J21: =J3+J4+J5+J10+J11+J14+J15+J18 | K21: =K3+K4+K5+K10+K11+K14+K15+K18 | ... O21: =O3+O4+O5+O10+O11+O14+O15+O18 | P21: =SUM(D21:O21) | R21: 2 Directors + 2 Youth Mentors + baseline
A22: IDEAL BUDGET TOTAL | D22: =D21+D6+D7 | E22: =E21+E6+E7 | F22: =F21+F6+F7 | G22: =G21+G6+G7 | H22: =H21+H6+H7 | I22: =I21+I6+I7 | J22: =J21+J6+J7 | K22: =K21+K6+K7 | ... O22: =O21+O6+O7 | P22: =SUM(D22:O22) | R22: Add 2 more Mentors + Teen Coordinator

Sheet Sheet1

Sheet Revenue Forecast
A1: Category | B1: Line Item | C1: Nov | D1: Dec | E1: Jan | F1: Feb | G1: Mar | H1: Apr | I1: May | J1: Jun | K1: Jul | L1: Aug | M1: Sep | N1: Oct | O1: Total | P1: Restriction | Q1: Confidence | R1: Notes
A2: Earned | B2: Participant Fees | C2: =$B$11 | D2: =$B$11 | E2: =$B$11 | F2: =$B$11 | G2: =$B$11 | H2: =$B$11 | I2: =$B$11 | J2: =$B$11 | ... N2: =$B$11 | O2: =SUM(C2:N2) | P2: Unrestricted | Q2: Medium | R2: Placeholder billing
A3: Government | B3: City Support (Operating Subsidy) | C3: 0 | D3: 0 | E3: 0 | F3: 0 | G3: 0 | H3: 0 | I3: 0 | J3: 0 | K3: 0 | L3: 0 | M3: 0 | N3: 0 | O3: =SUM(C3:N3) | P3: Restricted | Q3: High | R3: Awaiting commitments
A4: Contributions | B4: Grants & Contributions | C4: 0 | D4: 0 | E4: 0 | F4: 0 | G4: 0 | H4: 0 | I4: 0 | J4: 0 | K4: 0 | L4: 0 | M4: 0 | N4: 0 | O4: =SUM(C4:N4) | P4: Restricted | Q4: Medium | R4: Pending applications
A7: Revenue Calculation:
A8: Total enrollment | B8: 425
A9: Cost per participant | B9: 100
A10: Annual revenue | B10: =B8*B9
A11: Monthly revenue | B11: =B10/12

Sheet Cash Flow
A1: Month | B1: Beginning Cash | C1: Cash In | D1: Cash Out | E1: Net Change | F1: Ending Cash | G1: Minimum Target | H1: Variance | I1: Notes
A2: Jul | B2: =Assumptions!C6 | C2: ='Revenue Forecast'!B2+'Revenue Forecast'!B3+'Revenue Forecast'!B4 | D2: ='Expense Detail'!D2+'Expense Detail'!D3+'Expense Detail'!D4 | E2: =C2-D2 | F2: =B2+E2 | G2: =Assumptions!C6*0.25 | H2: =F2-G2 | I2: Placeholder cash forecast
A3: Aug | B3: =F2 | C3: ='Revenue Forecast'!C2+'Revenue Forecast'!C3+'Revenue Forecast'!C4 | D3: ='Expense Detail'!E2+'Expense Detail'!E3+'Expense Detail'!E4 | E3: =C3-D3 | F3: =B3+E3 | G3: =Assumptions!C6*0.25 | H3: =F3-G3 | I3: Placeholder cash forecast
A4: Sep | B4: =F3 | C4: ='Revenue Forecast'!D2+'Revenue Forecast'!D3+'Revenue Forecast'!D4 | D4: ='Expense Detail'!F2+'Expense Detail'!F3+'Expense Detail'!F4 | E4: =C4-D4 | F4: =B4+E4 | G4: =Assumptions!C6*0.25 | H4: =F4-G4 | I4: Placeholder cash forecast
A5: Oct | B5: =F4 | C5: ='Revenue Forecast'!E2+'Revenue Forecast'!E3+'Revenue Forecast'!E4 | D5: ='Expense Detail'!G2+'Expense Detail'!G3+'Expense Detail'!G4 | E5: =C5-D5 | F5: =B5+E5 | G5: =Assumptions!C6*0.25 | H5: =F5-G5 | I5: Placeholder cash forecast
A6: Nov | B6: =F5 | C6: ='Revenue Forecast'!F2+'Revenue Forecast'!F3+'Revenue Forecast'!F4 | D6: ='Expense Detail'!H2+'Expense Detail'!H3+'Expense Detail'!H4 | E6: =C6-D6 | F6: =B6+E6 | G6: =Assumptions!C6*0.25 | H6: =F6-G6 | I6: Placeholder cash forecast
A7: Dec | B7: =F6 | C7: ='Revenue Forecast'!G2+'Revenue Forecast'!G3+'Revenue Forecast'!G4 | D7: ='Expense Detail'!I2+'Expense Detail'!I3+'Expense Detail'!I4 | E7: =C7-D7 | F7: =B7+E7 | G7: =Assumptions!C6*0.25 | H7: =F7-G7 | I7: Placeholder cash forecast
A8: Jan | B8: =F7 | C8: ='Revenue Forecast'!H2+'Revenue Forecast'!H3+'Revenue Forecast'!H4 | D8: ='Expense Detail'!J2+'Expense Detail'!J3+'Expense Detail'!J4 | E8: =C8-D8 | F8: =B8+E8 | G8: =Assumptions!C6*0.25 | H8: =F8-G8 | I8: Placeholder cash forecast
A9: Feb | B9: =F8 | C9: ='Revenue Forecast'!I2+'Revenue Forecast'!I3+'Revenue Forecast'!I4 | D9: ='Expense Detail'!K2+'Expense Detail'!K3+'Expense Detail'!K4 | E9: =C9-D9 | F9: =B9+E9 | G9: =Assumptions!C6*0.25 | H9: =F9-G9 | I9: Placeholder cash forecast
A10: Mar | B10: =F9 | C10: ='Revenue Forecast'!J2+'Revenue Forecast'!J3+'Revenue Forecast'!J4 | D10: ='Expense Detail'!L2+'Expense Detail'!L3+'Expense Detail'!L4 | E10: =C10-D10 | F10: =B10+E10 | G10: =Assumptions!C6*0.25 | H10: =F10-G10 | I10: Placeholder cash forecast
A11: Apr | B11: =F10 | C11: ='Revenue Forecast'!K2+'Revenue Forecast'!K3+'Revenue Forecast'!K4 | D11: ='Expense Detail'!M2+'Expense Detail'!M3+'Expense Detail'!M4 | E11: =C11-D11 | F11: =B11+E11 | G11: =Assumptions!C6*0.25 | H11: =F11-G11 | I11: Placeholder cash forecast
A12: May | B12: =F11 | C12: ='Revenue Forecast'!L2+'Revenue Forecast'!L3+'Revenue Forecast'!L4 | D12: ='Expense Detail'!N2+'Expense Detail'!N3+'Expense Detail'!N4 | E12: =C12-D12 | F12: =B12+E12 | G12: =Assumptions!C6*0.25 | H12: =F12-G12 | I12: Placeholder cash forecast
A13: Jun | B13: =F12 | C13: ='Revenue Forecast'!M2+'Revenue Forecast'!M3+'Revenue Forecast'!M4 | D13: ='Expense Detail'!O2+'Expense Detail'!O3+'Expense Detail'!O4 | E13: =C13-D13 | F13: =B13+E13 | G13: =Assumptions!C6*0.25 | H13: =F13-G13 | I13: Placeholder cash forecast

Sheet Scenario Analysis
A1: Budget Type | B1: Scenario | C1: Revenue Multiplier | D1: Enrollment Multiplier | E1: Expense Escalation | F1: Projected Surplus/Deficit | G1: Notes
A2: Necessity | B2: Base | C2: 1 | D2: 1 | E2: ='Revenue Forecast'!O2+'Revenue Forecast'!O3+'Revenue Forecast'!O4-'Expense Detail'!Q2-'Expense Detail'!Q3-'Expense Detail'!Q4 | F2: Baseline assumption | G2: Without Teen Coordinator
A3: Necessity | B3: Conservative | C3: 0.95 | D3: 1.02 | E3: =B3*('Revenue Forecast'!O2+'Revenue Forecast'!O3+'Revenue Forecast'!O4)-(C3*'Expense Detail'!Q2 + C3*'Expense Detail'!Q3 + D3*'Expense Detail'!Q4) | F3: Lower enrollment, higher costs | G3: Without Teen Coordinator
A4: Necessity | B4: Stretch | C4: 1.05 | D4: 0.98 | E4: =B4*('Revenue Forecast'!O2+'Revenue Forecast'!O3+'Revenue Forecast'!O4)-(C4*'Expense Detail'!Q2 + C4*'Expense Detail'!Q3 + D4*'Expense Detail'!Q4) | F4: Higher enrollment, small savings | G4: Without Teen Coordinator
A5: Ideal | B5: Base | C5: 1 | D5: 1 | E5: 1 | G5: With Teen Coordinator (+$43,243)
A6: Ideal | B6: Conservative | C6: 0.9 | D6: 0.95 | E6: 1.02 | G6: With Teen Coordinator (+$43,243)
A7: Ideal | B7: Stretch | C7: 1.1 | D7: 1.05 | E7: 0.98 | G7: With Teen Coordinator (+$43,243)

Sheet Checklist
A1: Item | B1: Owner | C1: Status | D1: Due Date | E1: Notes
A2: Confirm fiscal year with city | B2: Matthew | C2: In Progress
A3: Gather enrollment projections | B3: Program Lead | C3: Not Started
A4: Secure facility MOU | B4: City | C4: Not Started

Sheet Operations & Staffing Schedule
A1: OPERATIONS & STAFFING SCHEDULE
A3: Period | B3: Operating Hours | C3: Days/Week | D3: Weeks/Year | E3: Staff Position | F3: Number of Staff | G3: Total Staff On-Site | H3: Notes
A4: SCHOOL YEAR - NECESSITY
A5: After-School | B5: 2:00 PM - 6:00 PM | C5: 5 | D5: 38 | E5: Program Director | F5: 1 | G5: 4 | H5: Minimum viable staffing - 2 mentors
E6: Director of Youth Development | F6: 1
E7: Youth Mentors | F7: 2
A9: SCHOOL YEAR - IDEAL
A10: After-School | B10: 2:00 PM - 6:00 PM | C10: 5 | D10: 38 | E10: Program Director | F10: 1 | G10: 6 | H10: Full staffing capacity
E11: Director of Youth Development | F11: 1
E12: Youth Mentors | F12: 4 | H12: 4 mentors for better ratios
E13: Teen Coordinator | F13: 1 | H13: Specialized teen programming
A15: SUMMER - NECESSITY
A16: Full Day | B16: 7:00 AM - 6:00 PM | C16: 5 | D16: 14 | E16: Program Director | F16: 1 | G16: 4 | H16: Extended summer hours - 2 mentors
E17: Director of Youth Development | F17: 1
E18: Youth Mentors | F18: 2
A20: SUMMER - IDEAL
A21: Full Day | B21: 7:00 AM - 6:00 PM | C21: 5 | D21: 14 | E21: Program Director | F21: 1 | G21: 6 | H21: Full summer programming
E22: Director of Youth Development | F22: 1
E23: Youth Mentors | F23: 4 | H23: 4 mentors for activities
E24: Teen Coordinator | F24: 1 | H24: Teen-specific activities
A26: SCHOOL BREAKS & INSERVICE DAYS - NECESSITY
A27: Full Day | B27: 7:00 AM - 6:00 PM | C27: Variable | D27: ~15 days/year | E27: Program Director | F27: 1 | G27: 4 | H27: Winter/Spring breaks, inservice - 2 mentors
E28: Director of Youth Development | F28: 1
E29: Youth Mentors | F29: 2
A31: SCHOOL BREAKS & INSERVICE DAYS - IDEAL
A32: Full Day | B32: 7:00 AM - 6:00 PM | C32: Variable | D32: ~15 days/year | E32: Program Director | F32: 1 | G32: 6 | H32: Special programming for breaks
E33: Director of Youth Development | F33: 1
E34: Youth Mentors | F34: 4 | H34: Field trips, special activities
E35: Teen Coordinator | F35: 1 | H35: Teen-focused programs
A37: ANNUAL OPERATING SUMMARY
A38: Total Operating Days (Approximate):
B39: School Year (38 weeks × 5 days) | C39: 190 | D39: days
B40: Summer (14 weeks × 5 days) | C40: 70 | D40: days
B41: School Breaks/Inservice | C41: 15 | D41: days (estimated)
B42: TOTAL OPERATING DAYS | C42: =C39+C40+C41 | D42: days/year
